ipanema/__init__.py
ipanema/__main__.py
ipanema/languages.sqlite
ipanema/models.py
ipanema-0.2.20190403.dist-info/LICENSE
ipanema-0.2.20190403.dist-info/METADATA
ipanema-0.2.20190403.dist-info/WHEEL
ipanema-0.2.20190403.dist-info/top_level.txt
ipanema-0.2.20190403.dist-info/RECORD
