Metadata-Version: 2.1
Name: ipanema
Version: 0.2.20190403
Summary: Packaged language data from Wiktionary
Home-page: https://gitlab.com/jberkel/ipanema
Author: Jan Berkel
Author-email: jan@berkel.fr
License: UNKNOWN
Platform: UNKNOWN
Classifier: Programming Language :: Python :: 3
Classifier: License :: OSI Approved :: MIT License
Classifier: Operating System :: OS Independent
Requires-Python: >=3
Requires-Dist: peewee (>=3.9.0)
